{
    "dataset_alpha": {
        "name": "数据集 Alpha",
        "versions": {
            "v1": {
                "name": "版本 v1.0",
                "metrics": {
                    "chinese": {
                        "name": "中文指标 (Chinese)",
                        "list": [
                            {
                                "id": "c_mos",
                                "name": "MOS ↑",
                                "sort": "desc"
                            },
                            {
                                "id": "c_wer",
                                "name": "CER ↓",
                                "sort": "asc"
                            }
                        ]
                    },
                    "english": {
                        "name": "英文指标 (English)",
                        "list": [
                            {
                                "id": "e_mos",
                                "name": "MOS ↑",
                                "sort": "desc"
                            },
                            {
                                "id": "e_wer",
                                "name": "WER ↓",
                                "sort": "asc"
                            }
                        ]
                    }
                },
                "models": [
                    {
                        "name": "模型 A",
                        "paper": "论文 A",
                        "scores": {
                            "c_mos": 4.5,
                            "c_wer": 5.1,
                            "e_mos": 4.6,
                            "e_wer": 4.8
                        }
                    },
                    {
                        "name": "模型 B",
                        "paper": "论文 B",
                        "scores": {
                            "c_mos": 4.3,
                            "c_wer": 4.9,
                            "e_mos": 4.7,
                            "e_wer": 4.5
                        }
                    }
                ]
            },
            "v2": {
                "name": "版本 v2.0",
                "metrics": {
                    "chinese": {
                        "name": "中文指标 (Chinese)",
                        "list": [
                            {
                                "id": "c_mos",
                                "name": "MOS ↑",
                                "sort": "desc"
                            },
                            {
                                "id": "c_wer",
                                "name": "CER ↓",
                                "sort": "asc"
                            }
                        ]
                    },
                    "english": {
                        "name": "英文指标 (English)",
                        "list": [
                            {
                                "id": "e_mos",
                                "name": "MOS ↑",
                                "sort": "desc"
                            },
                            {
                                "id": "e_wer",
                                "name": "WER ↓",
                                "sort": "asc"
                            }
                        ]
                    }
                },
                "models": [
                    {
                        "name": "模型 A",
                        "paper": "论文 A",
                        "scores": {
                            "c_mos": 4.5,
                            "c_wer": 5.1,
                            "e_mos": 4.6,
                            "e_wer": 4.8
                        }
                    },
                    {
                        "name": "模型 B",
                        "paper": "论文 B",
                        "scores": {
                            "c_mos": 4.3,
                            "c_wer": 4.9,
                            "e_mos": 4.7,
                            "e_wer": 4.5
                        }
                    }
                ]
            }
        }
    },
    "dataset_beta": {
        "name": "数据集 Beta",
        "versions": {
            "default": {
                "name": "主测试集",
                "metrics": {
                    "general": {
                        "name": "通用指标",
                        "list": [
                            {
                                "id": "similarity",
                                "name": "相似度 ↑",
                                "sort": "desc"
                            },
                            {
                                "id": "f0_rmse",
                                "name": "F0 RMSE ↓",
                                "sort": "asc"
                            }
                        ]
                    },
                    "robustness": {
                        "name": "鲁棒性",
                        "list": [
                            {
                                "id": "noise_snr",
                                "name": "噪声 SNR ↑",
                                "sort": "desc"
                            }
                        ]
                    }
                },
                "models": [
                    {
                        "name": "模型 D",
                        "paper": "论文 D",
                        "scores": {
                            "similarity": 0.95,
                            "f0_rmse": 0.18,
                            "noise_snr": 25.1
                        }
                    },
                    {
                        "name": "模型 E",
                        "paper": "论文 E",
                        "scores": {
                            "similarity": 0.93,
                            "f0_rmse": 0.22,
                            "noise_snr": 24.5
                        }
                    }
                ]
            }
        }
    }
}